README.rst
setup.py
django_tasker_unisender/__init__.py
django_tasker_unisender/admin.py
django_tasker_unisender/apps.py
django_tasker_unisender/models.py
django_tasker_unisender/tests.py
django_tasker_unisender/unisender.py
django_tasker_unisender.egg-info/PKG-INFO
django_tasker_unisender.egg-info/SOURCES.txt
django_tasker_unisender.egg-info/dependency_links.txt
django_tasker_unisender.egg-info/requires.txt
django_tasker_unisender.egg-info/top_level.txt
django_tasker_unisender/migrations/0001_initial.py
django_tasker_unisender/migrations/__init__.py
tests/__init__.py
tests/admin.py
tests/models.py
tests/settings.py
tests/test_base.py
tests/test_unisender.py
tests/urls.py
tests/wsgi.py